kisti_dongmin_naver_news_crawler/__init__.py
kisti_dongmin_naver_news_crawler/server.py
kisti_dongmin_naver_news_crawler-0.5.0.dist-info/METADATA
kisti_dongmin_naver_news_crawler-0.5.0.dist-info/WHEEL
kisti_dongmin_naver_news_crawler-0.5.0.dist-info/entry_points.txt
kisti_dongmin_naver_news_crawler-0.5.0.dist-info/RECORD
