Metadata-Version: 2.4
Name: kisti-dongmin-naver-news-crawler
Version: 0.5.0
Summary: Add your description here
Requires-Python: >=3.11
Requires-Dist: beautifulsoup4>=4.13.4
Requires-Dist: build>=1.3.0
Requires-Dist: mcp[cli]>=1.12.3
Requires-Dist: requests>=2.32.4
Requires-Dist: twine>=6.1.0
